{
  "project_info": {
    "project_number": "310125480312",
    "project_id": "hungerhub-56610",
    "storage_bucket": "hungerhub-56610.firebasestorage.app"
  },
  "client": [
    {
      "client_info": {
        "mobilesdk_app_id": "1:310125480312:android:850b12350f8c60ae01608d",
        "android_client_info": {
          "package_name": "com.example.hungerhub"
        }
      },
      "oauth_client": [],
      "api_key": [
        {
          "current_key": "AIzaSyC7JgwCKWFxKq2XrH0JWfEi9jOaxdrPt6M"
        }
      ],
      "services": {
        "appinvite_service": {
          "other_platform_oauth_client": []
        }
      }
    }
  ],
  "configuration_version": "1"
}